LICENSE.txt
MANIFEST.in
README.rst
datestamp.py
setup.py
datestamp.egg-info/PKG-INFO
datestamp.egg-info/SOURCES.txt
datestamp.egg-info/dependency_links.txt
datestamp.egg-info/top_level.txt