Metadata-Version: 2.1
Name: datestamp
Version: 2020.2.9
Summary: Automated software version generator and replacer based on `year.month.day` as its format.
Home-page: https://github.com/YoSTEALTH/datestamp
Author: STEALTH
License: UNKNOWN
Platform: UNKNOWN
Classifier: License :: Public Domain
Classifier: Intended Audience :: Developers
Classifier: Development Status :: 3 - Alpha
Classifier: Programming Language :: Python :: 3.6
Classifier: Programming Language :: Python :: 3.7
Classifier: Programming Language :: Python :: 3.8
Classifier: Topic :: Software Development :: Libraries :: Python Modules
Requires-Python: >=3.6
